{
  "main": {
    "id": "048acf6eac25de99",
    "type": "split",
    "children": [
      {
        "id": "c21a23f9b88d7e1c",
        "type": "tabs",
        "children": [
          {
            "id": "05dc4b1ae909aa7b",
            "type": "leaf",
            "state": {
              "type": "markdown",
              "state": {
                "file": "云计算/容器/Kubernetes in Action/第十一章：Kubernetes API服务器的安全防护.md",
                "mode": "source",
                "source": false
              }
            }
          },
          {
            "id": "3ae627c212dc32b9",
            "type": "leaf",
            "state": {
              "type": "markdown",
              "state": {
                "file": "云计算/容器/Kubernetes in Action/第七章：从应用访问pod元数据及其他资源.md",
                "mode": "source",
                "source": false
              }
            }
          },
          {
            "id": "052af1da6a047431",
            "type": "leaf",
            "state": {
              "type": "markdown",
              "state": {
                "file": "云计算/容器/Kubernetes in Action/第十章：了解Kubernetes机制.md",
                "mode": "source",
                "source": false
              }
            }
          }
        ]
      }
    ],
    "direction": "vertical"
  },
  "left": {
    "id": "6f7f47ab284ac448",
    "type": "split",
    "children": [
      {
        "id": "bfd1998d4eb68d1a",
        "type": "tabs",
        "children": [
          {
            "id": "4f0f2ca6323c33fe",
            "type": "leaf",
            "state": {
              "type": "file-explorer",
              "state": {
                "sortOrder": "alphabetical"
              }
            }
          },
          {
            "id": "ff0141aac6aabeb4",
            "type": "leaf",
            "state": {
              "type": "search",
              "state": {
                "query": "",
                "matchingCase": false,
                "explainSearch": false,
                "collapseAll": false,
                "extraContext": false,
                "sortOrder": "alphabetical"
              }
            }
          },
          {
            "id": "943e8e2ffccda74f",
            "type": "leaf",
            "state": {
              "type": "bookmarks",
              "state": {}
            }
          }
        ]
      }
    ],
    "direction": "horizontal",
    "width": 337.5
  },
  "right": {
    "id": "a689601275098279",
    "type": "split",
    "children": [
      {
        "id": "93fe5a4b68d4d3aa",
        "type": "tabs",
        "children": [
          {
            "id": "0d64ace92237c3dc",
            "type": "leaf",
            "state": {
              "type": "backlink",
              "state": {
                "file": "云计算/容器/Kubernetes in Action/第十一章：Kubernetes API服务器的安全防护.md",
                "collapseAll": false,
                "extraContext": false,
                "sortOrder": "alphabetical",
                "showSearch": false,
                "searchQuery": "",
                "backlinkCollapsed": false,
                "unlinkedCollapsed": true
              }
            }
          },
          {
            "id": "079d57d0612ac669",
            "type": "leaf",
            "state": {
              "type": "outgoing-link",
              "state": {
                "file": "云计算/容器/Kubernetes in Action/第十一章：Kubernetes API服务器的安全防护.md",
                "linksCollapsed": false,
                "unlinkedCollapsed": true
              }
            }
          },
          {
            "id": "307df7045b48c172",
            "type": "leaf",
            "state": {
              "type": "tag",
              "state": {
                "sortOrder": "frequency",
                "useHierarchy": true
              }
            }
          },
          {
            "id": "874645832d36bcee",
            "type": "leaf",
            "state": {
              "type": "outline",
              "state": {
                "file": "云计算/容器/Kubernetes in Action/第十一章：Kubernetes API服务器的安全防护.md"
              }
            }
          }
        ],
        "currentTab": 3
      }
    ],
    "direction": "horizontal",
    "width": 200
  },
  "left-ribbon": {
    "hiddenItems": {
      "switcher:打开快速切换": false,
      "graph:查看关系图谱": false,
      "canvas:新建白板": false,
      "daily-notes:打开/创建今天的日记": false,
      "templates:插入模板": false,
      "command-palette:打开命令面板": false
    }
  },
  "active": "05dc4b1ae909aa7b",
  "lastOpenFiles": [
    "云计算/容器/Kubernetes in Action/image/第十一章：Kubernetes API服务器的安全防护_time_7.png",
    "云计算/容器/Kubernetes in Action/image/第十一章：Kubernetes API服务器的安全防护_time_6.png",
    "云计算/容器/Kubernetes in Action/image/第十一章：Kubernetes API服务器的安全防护_time_5.png",
    "云计算/容器/Kubernetes in Action/image/第十一章：Kubernetes API服务器的安全防护_time_4.png",
    "云计算/容器/Kubernetes in Action/image/第十一章：Kubernetes API服务器的安全防护_time_3.png",
    "云计算/容器/Kubernetes in Action/image/第十一章：Kubernetes API服务器的安全防护_time_2.png",
    "云计算/容器/Kubernetes in Action/image/第十一章：Kubernetes API服务器的安全防护_time_1.png",
    "云计算/容器/Kubernetes in Action/第七章：从应用访问pod元数据及其他资源.md",
    "云计算/容器/Kubernetes in Action/第六章：ConfigMap和Secret-配置应用程序.md",
    "云计算/容器/Kubernetes in Action/第十一章：Kubernetes API服务器的安全防护.md",
    "云计算/容器/Kubernetes in Action/第八章：Deployment-声明式的升级应用.md",
    "云计算/容器/Kubernetes in Action/第十章：了解Kubernetes机制.md",
    "云计算/容器/Kubernetes in Action/第三章：副本机制和控制器.md",
    "云计算/容器/Kubernetes in Action/第一章：Kubernetes介绍.md",
    "云计算/容器/Kubernetes in Action/第五章：卷-将磁盘挂载到容器.md",
    "云计算/容器/Kubernetes in Action/第四章：服务-让客户端发现pod并与之通信.md",
    "云计算/容器/Kubernetes in Action/第九章：StatefulSet-部署有状态的多副本应用.md",
    "云计算/容器/Kubernetes in Action/第二章：pod-运行于kubernetes中的容器.md",
    "云计算/容器/Kubernetes in Action/image/第八章：Deployment-声明式的升级应用_time_1.png",
    "云计算/容器/Kubernetes in Action/image/第七章：从应用访问pod元数据及其他资源_time_2.png",
    "云计算/容器/Kubernetes in Action/image/第七章：从应用访问pod元数据及其他资源_time_1.png",
    "云计算/容器/Kubernetes in Action/image/第五章：卷-将磁盘挂载到容器_time_2.png",
    "分布式版本控制系统/git.md",
    "go/基础/golang.md",
    "云计算/容器/云原生/k8s极速版.md",
    "云计算/容器/云原生/Kubernetes.md",
    "云计算/容器/云原生/云原生.md",
    "云计算/容器/云原生/Docker.md",
    "云计算/容器/容器网络/kubernetes网络.md",
    "疑惑.md",
    "git.md",
    "image/git",
    "tmp1718440101571_Git_time_7.md",
    "Git.md"
  ]
}